grafana_dashboards/__init__.py
grafana_dashboards/builder.py
grafana_dashboards/cache.py
grafana_dashboards/cmd.py
grafana_dashboards/config.py
grafana_dashboards/parser.py
grafana_dashboards/grafana/__init__.py
grafana_dashboards/grafana/dashboard.py
grafana_dashboards/grafana/datasource.py
grafana_dashboards/grafana/utils.py
grafana_dashboards/schema/__init__.py
grafana_dashboards/schema/dashboard.py
grafana_dashboards/schema/datasource.py
grafana_dashboards/schema/links.py
grafana_dashboards/schema/row.py
grafana_dashboards/schema/panel/__init__.py
grafana_dashboards/schema/panel/base.py
grafana_dashboards/schema/panel/dashlist.py
grafana_dashboards/schema/panel/graph.py
grafana_dashboards/schema/panel/row.py
grafana_dashboards/schema/panel/singlestat.py
grafana_dashboards/schema/panel/text.py
grafana_dashboards/schema/template/__init__.py
grafana_dashboards/schema/template/adhoc.py
grafana_dashboards/schema/template/base.py
grafana_dashboards/schema/template/custom.py
grafana_dashboards/schema/template/datasource.py
grafana_dashboards/schema/template/interval.py
grafana_dashboards/schema/template/query.py
grafyaml-0.0.9.dist-info/AUTHORS
grafyaml-0.0.9.dist-info/LICENSE
grafyaml-0.0.9.dist-info/METADATA
grafyaml-0.0.9.dist-info/WHEEL
grafyaml-0.0.9.dist-info/entry_points.txt
grafyaml-0.0.9.dist-info/pbr.json
grafyaml-0.0.9.dist-info/top_level.txt
grafyaml-0.0.9.dist-info/RECORD
