Metadata-Version: 2.1
Name: grafyaml
Version: 0.0.9
Summary: Grafyaml takes simple descriptions of Grafana dashboards in YAML format, and uses them to configure grafana.
Home-page: http://docs.openstack.org/infra/system-config/grafyaml.html
Author: OpenStack Infrastructure Team
Author-email: openstack-infra@lists.openstack.org
License: UNKNOWN
Platform: UNKNOWN
Classifier: Development Status :: 3 - Alpha
Classifier: Environment :: Console
Classifier: Intended Audience :: Developers
Classifier: Intended Audience :: Information Technology
Classifier: Intended Audience :: System Administrators
Classifier: License :: OSI Approved :: Apache Software License
Classifier: Operating System :: OS Independent
Classifier: Programming Language :: Python
Classifier: Programming Language :: Python :: 3
Classifier: Programming Language :: Python :: 3.3
Classifier: Programming Language :: Python :: 3.5
Classifier: Programming Language :: Python :: 3.6
Classifier: Programming Language :: Python :: 3.7
Classifier: Programming Language :: Python :: 3.8
Classifier: Programming Language :: Python :: 3.10
Classifier: Topic :: Utilities
Requires-Dist: PyYAML (>=3.1.0)
Requires-Dist: dogpile.cache
Requires-Dist: pbr (!=2.1.0,>=2.0.0)
Requires-Dist: python-slugify
Requires-Dist: requests
Requires-Dist: six (>=1.6.0)
Requires-Dist: voluptuous (>=0.13.1)
